cliptext_st/__init__.py
cliptext_st-0.1.2.dist-info/licenses/LICENSE
cliptext_st-0.1.2.dist-info/METADATA
cliptext_st-0.1.2.dist-info/WHEEL
cliptext_st-0.1.2.dist-info/top_level.txt
cliptext_st-0.1.2.dist-info/RECORD
