Metadata-Version: 2.4
Name: cliptext_st
Version: 0.1.2
Summary: Small Python module for clipboard text utilities
Author-email: Saurabh Giri <skgvns8789@gmail.com>
License: MIT
Requires-Python: >=3.7
License-File: LICENSE
Requires-Dist: pyperclip
Dynamic: license-file
